csrfvalidators/__init__.py
csrfvalidators/src/__init__.py
csrfvalidators/src/validator.py
csrfvalidators-0.1.10.dist-info/METADATA
csrfvalidators-0.1.10.dist-info/WHEEL
csrfvalidators-0.1.10.dist-info/top_level.txt
csrfvalidators-0.1.10.dist-info/RECORD
