Metadata-Version: 2.1
Name: csrfvalidators
Version: 0.1.10
Summary: validation
Author: nxbz44
Author-email: nxbz44@yopmail.com
